awap2019/__init__.py
awap2019/board.py
awap2019/bot.py
awap2019/direction.py
awap2019/game.py
awap2019/state.py
awap2019/tile.py
awap2019/bots/__init__.py
awap2019/bots/bot.py
awap2019/bots/extrovert.py
awap2019/bots/follow.py
awap2019/bots/jittery.py
awap2019/bots/random.py
awap2019/bots/realistic.py
awap2019/bots/still.py
awap2019/bots/algs/__init__.py
awap2019/bots/algs/algorithms.py
awap2019-2.1.1.dist-info/LICENSE
awap2019-2.1.1.dist-info/METADATA
awap2019-2.1.1.dist-info/WHEEL
awap2019-2.1.1.dist-info/top_level.txt
awap2019-2.1.1.dist-info/RECORD
