Metadata-Version: 2.1
Name: awap2019
Version: 2.1.1
Summary: Module for AWAP 2019.
Home-page: http://github.com/cuebeomc/awap2019
Author: ACM@CMU
Author-email: cuebeomc@andrew.cmu.edu
License: GPL
Platform: UNKNOWN
Requires-Dist: numpy
Requires-Dist: absl-py
Requires-Dist: matplotlib
Requires-Dist: scipy
